reldo/__init__.py
reldo/cli.py
reldo/defaults.py
reldo/reldo.py
reldo/models/ReviewConfig.py
reldo/models/ReviewResult.py
reldo/models/ReviewSession.py
reldo/models/__init__.py
reldo/services/LoggingService.py
reldo/services/PromptService.py
reldo/services/ReviewService.py
reldo/services/__init__.py
reldo/utils/__init__.py
reldo/utils/substitution.py
reldo-0.4.3.dist-info/METADATA
reldo-0.4.3.dist-info/WHEEL
reldo-0.4.3.dist-info/entry_points.txt
reldo-0.4.3.dist-info/licenses/LICENSE
reldo-0.4.3.dist-info/RECORD
