Metadata-Version: 2.4
Name: reldo
Version: 0.4.3
Summary: Claude-powered code review orchestrator that coordinates specialized review agents
Project-URL: Homepage, https://github.com/RasmusGodske/reldo
Project-URL: Documentation, https://github.com/RasmusGodske/reldo#readme
Project-URL: Repository, https://github.com/RasmusGodske/reldo
Project-URL: Issues, https://github.com/RasmusGodske/reldo/issues
Project-URL: Changelog, https://github.com/RasmusGodske/reldo/releases
Author: Rasmus Godske
Maintainer: Rasmus Godske
License-Expression: MIT
License-File: LICENSE
Keywords: ai,anthropic,automation,claude,cli,code-review,command-line,developer-tools,orchestrator,review
Classifier: Development Status :: 4 - Beta
Classifier: Environment :: Console
Classifier: Intended Audience :: Developers
Classifier: License :: OSI Approved :: MIT License
Classifier: Operating System :: OS Independent
Classifier: Programming Language :: Python :: 3
Classifier: Programming Language :: Python :: 3.11
Classifier: Programming Language :: Python :: 3.12
Classifier: Programming Language :: Python :: 3.13
Classifier: Topic :: Software Development :: Quality Assurance
Classifier: Topic :: Software Development :: Testing
Classifier: Topic :: Utilities
Classifier: Typing :: Typed
Requires-Python: >=3.11
Requires-Dist: claude-agent-sdk>=0.1.0
Provides-Extra: dev
Requires-Dist: mypy>=1.0; extra == 'dev'
Requires-Dist: pytest-asyncio>=0.23; extra == 'dev'
Requires-Dist: pytest>=8.0; extra == 'dev'
Requires-Dist: ruff>=0.1; extra == 'dev'
